{
    "screen_num": 1,
    "skill11": [145, 840],
    "skill12": [275, 840],
    "skill13": [405, 840],
    "skill21": [590, 840],
    "skill22": [720, 840],
    "skill23": [850, 840],
    "skill31": [1035, 840],
    "skill32": [1165, 840],
    "skill33": [1295, 840],
    "attack": [1630, 900],
    "cloth": [1720, 470],
    "master-skill1": [1310, 470],
    "master-skill2": [1440, 470],
    "master-skill3": [1560, 470],
    "switch_pick1": [245, 510],
    "switch_pick2": [520, 510],
    "switch_pick3": [800, 510],
    "switch_pick4": [1080, 510],
    "switch_pick5": [1350, 510],
    "switch_pick6": [1630, 510],
    "select1": [530, 640],
    "select2": [940, 640],
    "select3": [1370, 640],
    "ult1": [620, 335],
    "ult2": [950, 335],
    "ult3": [1290, 335],
    "card1":[230,730],
    "card2":[620,730],
    "card3":[950,730],
    "card4":[1290,730],
    "card5":[1650,730]
}
